{"schema":1,"generated_at":"2026-07-08T03:47:11.591680+00:00","dataset_generated_at":"2026-07-08T03:46:42.560839+00:00","quality":{"total_rows":2000,"analysis_ready_rows":1847,"removed_rows":153,"missing_text":8,"short_text":451,"short_rate":0.2255,"exact_duplicate_rows":145,"duplicate_rate":0.0725,"topic_coverage":0.332,"language_count":27,"top_languages":[{"language":"english","count":922},{"language":"schinese","count":397},{"language":"russian","count":139},{"language":"brazilian","count":93},{"language":"spanish","count":75},{"language":"german","count":58},{"language":"french","count":54},{"language":"koreana","count":43},{"language":"polish","count":32},{"language":"japanese","count":30}],"games":[{"app_id":2246340,"name":"怪物猎人：荒野","rows":500,"positive_rate":0.666,"topic_coverage":0.432,"short_rate":0.206},{"app_id":553850,"name":"绝地潜兵 2","rows":500,"positive_rate":0.81,"topic_coverage":0.278,"short_rate":0.186},{"app_id":949230,"name":"都市：天际线 II","rows":500,"positive_rate":0.706,"topic_coverage":0.416,"short_rate":0.198},{"app_id":1091500,"name":"赛博朋克 2077","rows":500,"positive_rate":0.95,"topic_coverage":0.202,"short_rate":0.312}],"checks":[{"name":"有效文本进入模型","passed":true,"detail":"移除空文本 8 条"},{"name":"训练数据完成去重","passed":true,"detail":"移除重复及无效记录 153 条"},{"name":"主题覆盖可用","passed":false,"detail":"覆盖率 33.2%"},{"name":"多语言样本","passed":true,"detail":"覆盖 27 种语言"}]},"model":{"name":"Character TF-IDF + Logistic Regression","task":"Predict Steam recommended / not recommended labels from multilingual review text","model_rows":1847,"holdout":{"accuracy":0.8231,"precision":0.9085,"recall":0.8562,"f1":0.8816,"macro_f1":0.766,"confusion_matrix":[[67,27],[45,268]],"majority_baseline_accuracy":0.769,"train_rows":1440,"test_rows":407},"cross_game":[{"app_id":553850,"game":"绝地潜兵 2","train_rows":1386,"test_rows":461,"accuracy":0.8004,"precision":0.873,"recall":0.8777,"f1":0.8753,"macro_f1":0.6877,"confusion_matrix":[[46,47],[45,323]]},{"app_id":949230,"game":"都市：天际线 II","train_rows":1378,"test_rows":469,"accuracy":0.7036,"precision":0.7688,"recall":0.8185,"f1":0.7928,"macro_f1":0.6361,"confusion_matrix":[[64,80],[59,266]]},{"app_id":1091500,"game":"赛博朋克 2077","train_rows":1412,"test_rows":435,"accuracy":0.8161,"precision":0.9714,"recall":0.8293,"f1":0.8947,"macro_f1":0.5837,"confusion_matrix":[[15,10],[70,340]]},{"app_id":2246340,"game":"怪物猎人：荒野","train_rows":1365,"test_rows":482,"accuracy":0.7282,"precision":0.7577,"recall":0.8608,"f1":0.8059,"macro_f1":0.6763,"confusion_matrix":[[79,87],[44,272]]}],"feature_examples":{"positive":[" g","好玩","oo","y "," b","! ","a ","e ","！ ","ood","om"," 好"," 很","good","go"," good","可以"," fun"],"negative":["游戏","闪退","遊戲"," 卡","屎 "," 我","傻逼","逆天","德田","了 ","垃圾"," cra","纳塔","什么","as","rash","♥♥"," 史"]},"errors":[{"game":"绝地潜兵 2","language":"schinese","text":" ♥♥♥♥","actual":1,"predicted":0,"confidence":0.7539},{"game":"怪物猎人：荒野","language":"latam","text":"Esta horrible, la historia es mala con ganas y políticamente correcta, los personajes no tienen carisma. \n5.5 porque los gráficos soy muy buenos y  no se que valor tiene crear uno de los personajes mas molestos de la ficción pero ganas de volver a jugar la historia no me quedaron.","actual":0,"predicted":1,"confidence":0.7468},{"game":"都市：天际线 II","language":"english","text":"Negative review purely because of cost. I love this game, you definitely need a very good computer to enjoy it, but most content is paid, only buy it if you can throw away money and love this genre. I cannot give it a good review after spending $100+ for most the content","actual":0,"predicted":1,"confidence":0.7096},{"game":"都市：天际线 II","language":"schinese","text":"老是闪退","actual":1,"predicted":0,"confidence":0.7073},{"game":"怪物猎人：荒野","language":"spanish","text":"Lo he intentado con esta saga, con monster hunter world, rise y ahora wild y es imposible para mi, son los peores controles que he visto para un juego de peleas, lo siento pero no lo aguanto.","actual":0,"predicted":1,"confidence":0.7025},{"game":"都市：天际线 II","language":"german","text":"Inzwischen relativ spielbar und optimiert wenn man immer die Launcher Updates mitmacht. Nur ab knapp 200.000 Einwohner stürzt das Spiel gerne und auch öfter ab, aber ansonsten brauchbares Spiel.","actual":1,"predicted":0,"confidence":0.6982},{"game":"赛博朋克 2077","language":"english","text":"♥♥♥♥♥♥♥ Preem!","actual":1,"predicted":0,"confidence":0.6824},{"game":"怪物猎人：荒野","language":"schinese","text":"这欧米茄真是给爷打笑了，在它面前我就像个原始人","actual":1,"predicted":0,"confidence":0.6816},{"game":"绝地潜兵 2","language":"english","text":"Dying simulator if you try to play it without friends.  Not too much better with, IMO.  Your mileage may vary.","actual":0,"predicted":1,"confidence":0.6779},{"game":"绝地潜兵 2","language":"english","text":"its alright i guess but it gets really boring and repetitive after a few hours of playing","actual":0,"predicted":1,"confidence":0.6739},{"game":"都市：天际线 II","language":"schinese","text":"除了闪退没什么毛病","actual":1,"predicted":0,"confidence":0.6684},{"game":"怪物猎人：荒野","language":"brazilian","text":"gacha filho da puta","actual":0,"predicted":1,"confidence":0.6649},{"game":"赛博朋克 2077","language":"polish","text":"<2h gry i 2 bugi które uniemożliwiły mi grę: tekstury się nie załadowały np postaci i elementów interaktywnych przez co nie mogłem znaleść i użyć przycisku na windzie. Następnie po wejściu na zewnątrz włączylo sie coś jak slow time po czym widziałem pulsującą ikonkę mojego celu ale moja postać nie nie mogła poruszyć. Zwróciłem grę. Jeśli to jest poprawiona w","actual":0,"predicted":1,"confidence":0.6532},{"game":"都市：天际线 II","language":"schinese","text":"很棒的游戏，但是成就系统有许多Bug，优化也很拉垮，顶级移动端300K人口后就带不动了。","actual":1,"predicted":0,"confidence":0.6525},{"game":"怪物猎人：荒野","language":"french","text":"Bon déja comment dire le jeux et moche pas finit avec des bug puis les cinématique quond peut pas skip ou quand les perso te font aller à un point A mais qu'il vont à 2 à l'heure pour te montré un paysage pas interessent bref chiant quoi puis un seul monstre ma fait vibré le GoreMagala puis après des monstre re utiliser pour la centième fois une histoire nul","actual":0,"predicted":1,"confidence":0.6525},{"game":"都市：天际线 II","language":"english","text":"Let me be upfront: when Cities Skylines II launched in October 2023, I was deeply disappointed. Not just as a fan of the original, but as someone who felt genuinely let down by the people responsible for bringing it to market. Two and a half years on, with Iceflake Studios now at the helm, I find myself in the surprising position of writing something I didn'","actual":1,"predicted":0,"confidence":0.6482},{"game":"都市：天际线 II","language":"latam","text":"Como fan del primero me da mucha pena tener que escribir esto. Es realmente una pena que luego de tanto no logran sacar un segundo juego en condiciones. El primero le sobrepasa en todo. Graficamente no es tan novedoso, me sigue gustando mas el primero, aun en full. El rendimiento es lamentable, apenas vas por los 50k de personas y ya comienzas a notar los ti","actual":0,"predicted":1,"confidence":0.6413},{"game":"绝地潜兵 2","language":"schinese","text":"惊为天人的游戏，要是再开几个更高的难度就好了...........我想看到EDF那种怪海................","actual":1,"predicted":0,"confidence":0.6371},{"game":"绝地潜兵 2","language":"english","text":"game hasn't been good since 6 months after launch, bwraps.","actual":0,"predicted":1,"confidence":0.6358},{"game":"赛博朋克 2077","language":"italian","text":"♥♥♥♥ you arasaka\r\n","actual":1,"predicted":0,"confidence":0.6288},{"game":"都市：天际线 II","language":"turkish","text":"I might continue playing once Turkish language support arrives; I regret buying it.","actual":0,"predicted":1,"confidence":0.6287},{"game":"赛博朋克 2077","language":"english","text":"An unsurmountable loss for the cyberpunk genre. 2077 is purely vibes and you can experience the despair by how prettified it looks. This is the prettification of poverty in a way that's palatable for the poor.","actual":0,"predicted":1,"confidence":0.6269},{"game":"怪物猎人：荒野","language":"schinese","text":"The journeys of the Sapphire Star in MHW and the Caravan in MH4G once genuinely moved me.\nBut Monster Hunter Wilds not.","actual":0,"predicted":1,"confidence":0.6253},{"game":"赛博朋克 2077","language":"russian","text":"I couldn’t wait for you to come clear the cupboards\r\nBut now you’re going to leave with nothing but a sign\r\nAnother evening I’ll be sitting reading in between your lines\r\nBecause I miss you all the time\r\nSo, get away\r\nAnother way to feel what you didn’t want yourself to know\r\nAnd let yourself go\r\nYou know you didn’t lose your self-control\r\nLet’s start at the","actual":1,"predicted":0,"confidence":0.6166}]}}